csvs/__init__.py
csvs/__version__.py
csvs/csvs.py
csvs-0.1.1.dist-info/DESCRIPTION.rst
csvs-0.1.1.dist-info/METADATA
csvs-0.1.1.dist-info/RECORD
csvs-0.1.1.dist-info/WHEEL
csvs-0.1.1.dist-info/metadata.json
csvs-0.1.1.dist-info/top_level.txt
